entrain/.DS_Store
entrain/__init__.py
entrain/entrain_scvelo.py
entrain/entrain_spatial.py
entrain/entrain_spatial_plotting.py
entrain-0.0.79.dist-info/METADATA
entrain-0.0.79.dist-info/WHEEL
entrain-0.0.79.dist-info/RECORD
