Metadata-Version: 2.1
Name: entrain
Version: 0.0.79
Summary: A single-cell analysis package to elucidate environmental factors controlling cell differentiation in RNA velocity and spatial datasets.
Author-email: Wunna Kyaw <wunna.a.kyaw@gmail.com>
Maintainer-email: Wunna Kyaw <wunna.a.kyaw@gmail.com>
License: MIT License
Keywords: RNA,bioinformatics,differentiation,ligand,receptor,single cell,velocity
Classifier: Development Status :: 3 - Alpha
Classifier: Intended Audience :: Science/Research
Classifier: License :: OSI Approved :: GNU General Public License v3 (GPLv3)
Classifier: Natural Language :: English
Classifier: Programming Language :: Python :: 3.9
Classifier: Topic :: Scientific/Engineering :: Bio-Informatics
Requires-Python: >=3.9
Requires-Dist: anndata>=0.7.5
Requires-Dist: rpy2
Requires-Dist: scanpy>=1.5
Requires-Dist: scvelo
Requires-Dist: squidpy
Provides-Extra: labeltransfer
Requires-Dist: tangram-sc; extra == 'labeltransfer'
Provides-Extra: ligandreceptor
Requires-Dist: omnipath-pypath; extra == 'ligandreceptor'
